{
  "id": 10001,
  "owner": "TestUser",
  "timestamp": 0,
  "baselineId": 1,
  "name": "Scenario Lysekil",
  "changes": {},
  "ecosystemsToInclude": [
    2,
    24,
    25,
    3,
    13,
    20,
    30,
    34,
    5,
    6,
    1,
    4,
    8,
    10,
    11,
    12,
    14,
    15,
    21,
    22,
    23,
    26,
    27,
    28,
    29,
    31,
    32,
    33,
    7,
    9,
    16,
    17,
    18,
    19,
    0
  ],
  "pressuresToInclude": [
    12,
    14,
    56,
    10,
    11,
    13,
    64,
    8,
    9,
    19,
    6,
    7,
    23,
    1,
    21,
    59,
    0,
    3,
    4,
    5,
    66,
    16,
    17,
    18,
    20,
    58,
    61,
    65,
    62,
    63,
    15,
    67,
    2,
    25,
    60,
    22,
    24,
    57,
    68
  ],
  "normalization": {
    "type": "DOMAIN",
    "userDefinedValue": 1,
    "stdDevMultiplier": 0
  },
  "operation": 0,
  "areas": [
    {
      "id": 2,
      "changes": {
          "Habitat loss fish farm": {
            "type": "PRESSURE",
            "band": 12,
            "offset": 101
          }
	  },
      "feature": {
        "type": "Feature",
      "properties": {
        "title": "Storgrundet Höga kusten",
        "statePath": [
          "area",
          "MSP",
          "groups",
          "Areas",
          "areas",
          "Storgrundet Höga kusten"]
        },
        "geometry": {
        "type": "Polygon",
        "coordinates": [
          [
            [
              19.1368283673853,
              63.1148568619922
            ],
            [
              18.9845269400935,
              63.0989640061064
            ],
            [
              18.9845173911553,
              63.0989625404767
            ],
            [
              18.9200438801283,
              63.085851476231
            ],
            [
              18.943301214927,
              63.0987375001483
            ],
            [
              18.9997889759943,
              63.1299717535374
            ],
            [
              19.0563981948021,
              63.1611833276039
            ],
            [
              19.1131252360806,
              63.1923699596462
            ],
            [
              19.1514784146704,
              63.2090614938479
            ],
            [
              19.1612903653872,
              63.213327017389
            ],
            [
              19.1718016331878,
              63.2102573564203
            ],
            [
              19.1795281254387,
              63.2024472281431
            ],
            [
              19.1797346161192,
              63.1945874245096
            ],
            [
              19.1727826485253,
              63.1849069350774
            ],
            [
              19.1630009380578,
              63.1785177723216
            ],
            [
              19.1629853383279,
              63.1785051831593
            ],
            [
              19.1629725629309,
              63.1784897355765
            ],
            [
              19.1629631252316,
              63.1784720503167
            ],
            [
              19.1368283673853,
              63.1148568619922
            ]
          ]
        ]
      },
      "matrix": {
        "matrixType": "STANDARD"
      },
      "scenarioId": 10001,
      "excludedCoastal": null
    }
  ],
  "operationOptions": null,
  "latestCalculationId": null
}